[{"key": [2.4691, 2.4691], "value": 0.0}, {"key": [2.4692, 2.4692], "value": 0.5}, {"key": [2.4693, 2.5712], "value": 1.0}, {"key": [2.5713, 2.5713], "value": 0.5}, {"key": [2.5714, 2.7033], "value": 0.0}, {"key": [2.7034, 2.7034], "value": 0.5}, {"key": [2.7035, 2.7634], "value": 1.0}, {"key": [2.7635, 2.7635], "value": 0.5}, {"key": [2.7636, 2.8624], "value": 0.0}, {"key": [2.8625, 2.8625], "value": 0.5}, {"key": [2.8626, 2.9515], "value": 1.0}, {"key": [2.9516, 2.9516], "value": 0.5}, {"key": [2.9517, 2.9545], "value": 0.0}, {"key": [2.9546, 2.9546], "value": 0.5}, {"key": [2.9547, 3.0116], "value": 1.0}, {"key": [3.0117, 3.0117], "value": 1.5}, {"key": [3.0118, 3.0866], "value": 2.0}, {"key": [3.0867, 3.0867], "value": 1.5}, {"key": [3.0868, 3.1227], "value": 1.0}]