[{"key": [99.1525, 99.1525], "value": 0.5}, {"key": [99.1526, 99.2428], "value": 1.0}, {"key": [99.2429, 99.2429], "value": 0.5}, {"key": [99.243, 99.3389], "value": 0.0}, {"key": [99.339, 99.339], "value": 0.5}, {"key": [99.3391, 99.4319], "value": 1.0}, {"key": [99.432, 99.432], "value": 0.5}, {"key": [99.4321, 99.5123], "value": 0.0}, {"key": [99.5124, 99.5124], "value": 0.5}, {"key": [99.5125, 99.5813], "value": 1.0}, {"key": [99.5814, 99.5814], "value": 0.5}, {"key": [99.5815, 99.9234], "value": 0.0}, {"key": [99.9235, 99.9235], "value": 0.5}, {"key": [99.9236, 99.9988], "value": 1.0}, {"key": [99.9989, 99.9989], "value": 0.5}, {"key": [99.999, 100.1215], "value": 0.0}, {"key": [100.1216, 100.1216], "value": 0.5}, {"key": [100.1217, 100.2239], "value": 1.0}, {"key": [100.224, 100.224], "value": 0.5}, {"key": [100.2241, 100.2269], "value": 0.0}, {"key": [100.227, 100.227], "value": 0.5}, {"key": [100.2271, 100.3289], "value": 1.0}]